{
  "이란": {
    "sections": [
      {
        "heading": "호르무즈 라라크섬에 미사일 타격",
        "body": "이란 혁명수비대 산하 타스님 뉴스 등 이란 매체들이 미국이 호르무즈 해협 내 라라크섬에 미사일 공격을 가했다고 보도했다. 주민들이 섬 인근에서 폭발음을 들었으며, 이란 당국은 정확한 피해 범위와 영향 지점을 파악 중이다. 미국은 아직 이 공격 사실을 공식 확인하지 않고 있다."
      },
      {
        "heading": "미국·이스라엘, 추가 군사행동 예고",
        "body": "이스라엘 카츠 국방부 장관은 대이란 군사작전 재개 준비가 완료됐으며 필요시 세 번째 독자 공습도 단행할 수 있다고 밝혔다. 미국도 며칠 내 대이란 작전의 다음 단계를 준비하고 있으며 트럼프 대통령의 최종 결정을 기다리는 것으로 알려졌다. 네타냐후 총리와 트럼프 대통령은 전화 통화를 통해 중동 작전 공조를 이어 나가기로 합의했다."
      },
      {
        "heading": "뉴욕증시, 미·이란 충돌에 하락 마감",
        "body": "미·이란 무력 충돌 소식이 전해지면서 뉴욕 증시는 하락 마감했다. 유가 급등과 지정학적 불확실성이 겹치며 투자 심리가 위축됐다. 이란 핵시설에 대한 추가 공습 가능성과 그 여파를 두고 글로벌 금융시장의 변동성이 커지고 있다."
      }
    ],
    "sources": [
      {
        "title": "미군, 이란 라라크섬 미사일 공격…이란 통신",
        "url": "https://www.fnnews.com/news/202607222203092461"
      },
      {
        "title": "이스라엘 국방 \"대이란 군사작전 재개 준비…필요시 3차 공습\"",
        "url": "https://www.kmib.co.kr/article/view.asp?arcid=0030091397&code=61131111&sid1=int"
      },
      {
        "title": "美, 대이란 군사작전 다음 단계 준비…며칠 내 군사활동 확대 예상",
        "url": "https://www.fnnews.com/news/202607210454511674"
      }
    ],
    "headline": "미국, 이란 섬 미사일 공격",
    "generated_at": "2026-07-23 07:12 KST"
  },
  "강력": {
    "sections": [
      {
        "heading": "민주당 전대, '신천지 개입설' 폭탄",
        "body": "더불어민주당 8·17 전당대회 당권 경쟁 과정에서 김민석 의원이 \"반명, 분열주의, 신천지의 비밀 3자연합을 깨는 것이 이번 전대의 본질\"이라며 신천지 개입설을 공개적으로 제기했다. 이 발언은 삽시간에 당내 논란으로 번지며 일부 지지층 사이에서 정청래 의원과의 연루 의혹으로 증폭됐다. 정청래 의원 지지자들은 크게 반발하며 의혹 제기의 근거를 촉구하고 있다."
      },
      {
        "heading": "정청래, 강력 법적 대응 경고",
        "body": "정청래 의원은 의혹 제기를 \"황당한 네거티브\"라며 즉각 반발하고 무관용 원칙에 따른 법적 대응을 예고했다. 그는 \"내 이름을 대고 신천지 연루설을 제기하면 가장 강력한 법적 조치를 취하겠다\"며 이미 관련 허위 조작 뉴스에 대해 법적 조치에 착수했다고 밝혔다. 친청계 의원들도 가세해 근거 제시를 요구하며 맞섰다."
      },
      {
        "heading": "전당대회 네거티브 과열 우려",
        "body": "김민석 의원이 이후 \"신천지는 특정 후보를 지칭한 것이 아니다\"라며 한발 물러섰으나 정청래 의원은 법적 절차를 멈추지 않겠다는 입장을 유지했다. 민주당 전당대회가 정책 경쟁보다 상호 의혹 제기로 과열되는 양상을 보이면서 당 안팎에서 우려의 목소리가 나오고 있다."
      }
    ],
    "sources": [
      {
        "title": "정청래, 김민석 '신천지' 의혹제기에…\"용납 못해, 강력 응징할 것\"",
        "url": "https://www.pressian.com/pages/articles/2026072215392034018"
      },
      {
        "title": "정청래 \"지지자들 '내가 신천지 신도냐' 분노…김민석 '신천지설'은 해당 행위\"",
        "url": "https://www.khan.co.kr/article/202607222230001"
      },
      {
        "title": "김민석 '신천지 개입' 띄우자…정청래 \"가짜뉴스 무관용, 법적 대응\"",
        "url": "https://www.dailian.co.kr/news/view/1669146/%EA%B9%80%EB%AF%BC%EC%84%9D-%EC%8B%A0%EC%B2%9C%EC%A7%80-%EA%B0%9C%EC%9E%85-%EB%9D%84%EC%9A%B0%EC%9E%90%EC%A0%95%EC%B2%AD%EB%9E%98-%EA%B0%80%EC%A7%9C-2026"
      }
    ],
    "headline": "정청래, 김민석 신천지 의혹 제기에 강력 반발",
    "generated_at": "2026-07-23 07:12 KST"
  },
  "처리": {
    "sections": [
      {
        "heading": "2차 종합특검 연장법, 전원 찬성 가결",
        "body": "더불어민주당 주도로 2차 종합특검 연장법이 국회 본회의에서 처리됐다. 재석 의원 173명 전원 찬성으로 가결된 이 법안은 내란·김건희·채상병 등 3대 특검 수사 기간을 30일 추가 연장하는 내용을 골자로 한다. 국민의힘 의원들은 표결에 참여하지 않았다."
      },
      {
        "heading": "보완수사권 완전 폐지 강행 예고",
        "body": "민주당은 검사의 보완수사권을 완전히 폐지하는 형사소송법 개정안을 이르면 다음 주 처리하겠다며 \"타협 없이 처리하겠다\"는 입장을 재확인했다. 7월 말을 처리 목표로 법제사법위원회 심사를 이어가고 있으며, 국민의힘이 복귀하더라도 원점 논의는 없다는 입장을 못 박았다. 국민의힘은 필리버스터로 맞불을 놓으며 여야 간 대립이 이어지고 있다."
      },
      {
        "heading": "수사 공백 우려 속 여야 대치 장기화",
        "body": "민주당은 경찰 수사가 미흡할 경우 검사가 직접 수사하는 대신 재수사를 요구하고 피해자에게 이의제기권을 확대하는 방식으로 공백을 막겠다고 설명했다. 그러나 국민의힘은 이를 검찰 기능의 사실상 무력화라며 강하게 반대해 여야 충돌이 장기화되고 있다."
      }
    ],
    "sources": [
      {
        "title": "종합특검 연장법 與주도 처리…8월 23일까지 수사 연장",
        "url": "https://www.fnnews.com/news/202607211523539629"
      },
      {
        "title": "민주당, 보완수사권 폐지 밀어붙인다…\"국힘 복귀해도 원점 논의 없다\"",
        "url": "https://www.newdaily.co.kr/site/data/html/2026/07/22/2026072200176.html"
      },
      {
        "title": "민주당, 결국 다시 '보완수사권 폐지'로…\"檢 수사권 되살리면 안돼\"",
        "url": "https://www.pressian.com/pages/articles/2026072210041601678"
      }
    ],
    "headline": "민주, 보완수사권 폐지·특검 연장법 처리 강행",
    "generated_at": "2026-07-23 07:12 KST"
  },
  "재개": {
    "sections": [
      {
        "heading": "이스라엘, 대이란 3차 공습 준비 선언",
        "body": "이스라엘 카츠 국방부 장관은 공군 조종사 수료식 연설에서 \"이스라엘군은 대이란 군사작전 재개를 위한 경계 태세와 만반의 준비를 갖추고 있다\"고 밝혔다. 그는 제공권 유지와 위협 제거를 위해 필요하다면 세 번째 '청백 공습'도 단행할 준비가 돼 있다고 강조했다. 이스라엘은 앞서 이란에 두 차례 독자 공습을 단행한 바 있다."
      },
      {
        "heading": "미 국방부, 미사일 부족 은폐 의혹",
        "body": "미 국방부가 미사일 재고 부족 사실을 백악관에 숨긴 채 이란전을 재개했다는 의혹이 미국 내에서 제기되고 있다. 충분한 준비 없이 군사 행동을 확대하는 것 아니냐는 비판도 나오고 있으나, 관련 사실 여부는 아직 공식 확인되지 않은 상태다."
      },
      {
        "heading": "미국, 트럼프 결단 기다리며 다음 단계 준비",
        "body": "미국도 며칠 내 대이란 군사작전의 다음 단계에 돌입할 준비를 마친 것으로 알려졌으며, 최종 실행은 트럼프 대통령의 결정에 달린 것으로 전해진다. 네타냐후 총리와 트럼프 대통령이 전화 통화를 통해 중동 공조 방침을 확인했으며, 추가 작전 여부에 따라 중동 정세가 급변할 것으로 전망된다."
      }
    ],
    "sources": [
      {
        "title": "이스라엘 국방 \"대이란 군사작전 재개 준비…필요시 3차 공습\"",
        "url": "https://www.kmib.co.kr/article/view.asp?arcid=0030091397&code=61131111&sid1=int"
      },
      {
        "title": "이스라엘 국방 \"이란 군사작전 준비 마쳐\"…네타냐후 \"미국과 공조 합의\"",
        "url": "https://www.khan.co.kr/article/202607100713001/"
      },
      {
        "title": "美, 대이란 군사작전 다음 단계 준비…며칠 내 군사활동 확대 예상",
        "url": "https://www.fnnews.com/news/202607210454511674"
      }
    ],
    "headline": "이스라엘, 대이란 군사작전 재개 준비 선언",
    "generated_at": "2026-07-23 07:12 KST"
  },
  "머니투데이": {
    "sections": [
      {
        "heading": "탈원전·4대강, 반도체 클러스터의 발목을 잡다",
        "body": "호남 반도체 산단 조성의 핵심 성공 요건으로 인력·수자원·전력(인·수·전)이 꼽히는 가운데, 전임 정부의 탈원전 정책과 4대강 정비 논란이 '부메랑'이 됐다는 분석이 나왔다. 안정적인 전력과 수자원 공급이 흔들리면서 반도체 산단 경쟁력 확보에 차질이 우려된다는 지적이다. 이재명 정부는 2026년 1월 신규 원전 건설을 공식화하며 사실상 탈원전 노선을 폐기했지만, 정책 공백의 후유증은 여전히 남아 있다."
      },
      {
        "heading": "홈플러스, 67개 점포 전면 재개장…회생 정상화 총력",
        "body": "기업회생 절차 중인 홈플러스가 자금난으로 임시휴업에 들어갔던 전국 67개 핵심 점포를 모두 다시 열기로 했다. 홈플러스는 긴급운영자금 대출금이 들어오는 대로 상품 대금과 연체된 임대료를 우선 지급하고 영업을 정상화하겠다고 밝혔다. 온라인 배송은 수도권 16개 점포부터 재개하며, 매출이 낮은 37개 부실 점포는 회생 기간 중 순차적으로 폐점할 예정이다."
      },
      {
        "heading": "유가 급등에 뉴욕 증시 하락…나스닥 0.57%↓",
        "body": "22일(현지시간) 뉴욕 증시는 국제유가 급등과 중동 지정학적 리스크에 일제히 하락 마감했다. 나스닥 종합지수는 전 거래일보다 146.30포인트(0.57%) 내린 2만5690.90에, S&P500은 0.14% 떨어졌다. 예멘 후티가 사우디아라비아 원유 수송을 겨냥한 해상 봉쇄를 위협하면서 공급 차질 우려가 커졌고, 브렌트유와 WTI는 약 6주 만에 최고 수준으로 올랐다."
      }
    ],
    "sources": [
      {
        "title": "호남 반도체 산단 성공요건 '인·수·전'...부메랑 된 '탈원전·4대강' - 머니투데이",
        "url": "https://www.mt.co.kr/politics/2026/07/21/2026072018211938543"
      },
      {
        "title": "홈플러스, 임시휴업 67개 점포 모두 다시 연다 - 머니투데이",
        "url": "https://www.mt.co.kr/living/2026/07/22/2026072209124098812"
      },
      {
        "title": "[뉴욕증시 마감] 유가 급등·빅테크 실적 경계에 하락…나스닥 0.57%↓ - 아주경제",
        "url": "https://www.ajunews.com/view/20260723071208137"
      }
    ],
    "headline": "머니투데이, 탈원전·홈플러스 등 주요 이슈 보도",
    "generated_at": "2026-07-23 19:07 KST"
  }
}
